{
    "$help": "https://aka.ms/terminal-documentation",
    "$schema": "https://aka.ms/terminal-profiles-schema",
    "actions":
    [],
    "copyFormatting": "none",
    "copyOnSelect": false,
    "defaultProfile": "{0caa0dad-35be-5f56-a8ff-afceeeaa6101}",
    "initialCols": 90,
    "keybindings":
    [
        {
            "id": "Terminal.CopyToClipboard",
            "keys": "ctrl+c"
        },
        {
            "id": "Terminal.FindText",
            "keys": "ctrl+shift+f"
        },
        {
            "id": "Terminal.PasteFromClipboard",
            "keys": "ctrl+v"
        },
        {
            "id": "Terminal.DuplicatePaneAuto",
            "keys": "alt+shift+d"
        }
    ],
    "newTabMenu":
    [
        {
            "type": "remainingProfiles"
        }
    ],
    "profiles":
    {
        "defaults":
        {
            "bellStyle": "none"
        },
        "list":
        [
            {
                "colorScheme": "Aardvark Blue",
                "commandline": "%SystemRoot%\\System32\\WindowsPowerShell\\v1.0\\powershell.exe",
                "guid": "{61c54bbd-c2c6-5271-96e7-009a87ff44bf}",
                "hidden": false,
                "name": "Windows PowerShell"
            },
            {
                "colorScheme": "Monokai Remastered",
                "commandline": "%SystemRoot%\\System32\\cmd.exe",
                "font":
                {
                    "face": "FiraCode Nerd Font Mono",
                    "size": 12
                },
                "guid": "{0caa0dad-35be-5f56-a8ff-afceeeaa6101}",
                "hidden": false,
                "name": "Командная строка"
            },
            {
                "guid": "{b453ae62-4e3d-5e58-b989-0a998ec441b8}",
                "hidden": false,
                "name": "Azure Cloud Shell",
                "source": "Windows.Terminal.Azure"
            },
            {
                "colorScheme": "GruvboxDarkHard",
                "font":
                {
                    "face": "Hack Nerd Font Mono"
                },
                "guid": "{2ece5bfe-50ed-5f3a-ab87-5cd4baafed2b}",
                "hidden": false,
                "name": "Git Bash",
                "source": "Git",
                "startingDirectory": null
            },
            {
                "guid": "{6010ef2a-884e-5a64-bfd5-811947e98ecc}",
                "hidden": false,
                "name": "Developer Command Prompt for VS 18",
                "source": "Windows.Terminal.VisualStudio"
            },
            {
                "guid": "{0ec2c697-8210-53d8-ae62-9b92de162c56}",
                "hidden": false,
                "name": "Developer PowerShell for VS 18",
                "source": "Windows.Terminal.VisualStudio"
            },
            {
                "colorScheme": "Dimidium",
                "font":
                {
                    "face": "Agave Nerd Font Mono",
                    "size": 13
                },
                "guid": "{58ad8b0c-3ef8-5f4d-bc6f-13e4c00f2530}",
                "hidden": false,
                "name": "Debian",
                "source": "Windows.Terminal.Wsl",
                "startingDirectory": null
            }
        ]
    },
    "schemes":
    [
        {
            "background": "#090300",
            "black": "#090300",
            "blue": "#01A0E4",
            "brightBlack": "#5C5855",
            "brightBlue": "#807D7C",
            "brightCyan": "#CDAB53",
            "brightGreen": "#3A3432",
            "brightPurple": "#D6D5D4",
            "brightRed": "#E8BBD0",
            "brightWhite": "#F7F7F7",
            "brightYellow": "#4A4543",
            "cursorColor": "#A5A2A2",
            "cyan": "#B5E4F4",
            "foreground": "#A5A2A2",
            "green": "#01A252",
            "name": "3024 Night",
            "purple": "#A16A94",
            "red": "#DB2D20",
            "selectionBackground": "#4A4543",
            "white": "#A5A2A2",
            "yellow": "#FDED02"
        },
        {
            "background": "#102040",
            "black": "#191919",
            "blue": "#1370D3",
            "brightBlack": "#454545",
            "brightBlue": "#60A4EC",
            "brightCyan": "#60B6CB",
            "brightGreen": "#95DC55",
            "brightPurple": "#E26BE2",
            "brightRed": "#F05B50",
            "brightWhite": "#F7F7F7",
            "brightYellow": "#FFE763",
            "cursorColor": "#007ACC",
            "cyan": "#008EB0",
            "foreground": "#DDDDDD",
            "green": "#4B8C0F",
            "name": "Aardvark Blue",
            "purple": "#C43AC3",
            "red": "#AA342E",
            "selectionBackground": "#BFDBFE",
            "white": "#BEBEBE",
            "yellow": "#DBBA00"
        },
        {
            "background": "#111416",
            "black": "#000000",
            "blue": "#1093F5",
            "brightBlack": "#404040",
            "brightBlue": "#11B5F6",
            "brightCyan": "#00FFFF",
            "brightGreen": "#00FF00",
            "brightPurple": "#FF00FF",
            "brightRed": "#FF0000",
            "brightWhite": "#FFFFFF",
            "brightYellow": "#FFFF00",
            "cursorColor": "#BBBBBB",
            "cyan": "#00CDCD",
            "foreground": "#EEEEEC",
            "green": "#00CD00",
            "name": "Abernathy",
            "purple": "#CD00CD",
            "red": "#CD0000",
            "selectionBackground": "#EEEEEC",
            "white": "#FAEBD7",
            "yellow": "#CDCD00"
        },
        {
            "background": "#212121",
            "black": "#151515",
            "blue": "#6C99BB",
            "brightBlack": "#505050",
            "brightBlue": "#6C99BB",
            "brightCyan": "#7DD6CF",
            "brightGreen": "#7E8E50",
            "brightPurple": "#9F4E85",
            "brightRed": "#AC4142",
            "brightWhite": "#F5F5F5",
            "brightYellow": "#E5B567",
            "cursorColor": "#D0D0D0",
            "cyan": "#7DD6CF",
            "foreground": "#D0D0D0",
            "green": "#7E8E50",
            "name": "Afterglow",
            "purple": "#9F4E85",
            "red": "#AC4142",
            "selectionBackground": "#303030",
            "white": "#D0D0D0",
            "yellow": "#E5B567"
        },
        {
            "background": "#292520",
            "black": "#121418",
            "blue": "#1398B9",
            "brightBlack": "#675F54",
            "brightBlue": "#5FDAFF",
            "brightCyan": "#84F088",
            "brightGreen": "#98E036",
            "brightPurple": "#FF9269",
            "brightRed": "#FF645A",
            "brightWhite": "#F6F7EC",
            "brightYellow": "#E0D561",
            "cursorColor": "#F6F7EC",
            "cyan": "#509552",
            "foreground": "#E5C7A9",
            "green": "#85C54C",
            "name": "Earthsong",
            "purple": "#D0633D",
            "red": "#C94234",
            "selectionBackground": "#121418",
            "white": "#E5C6AA",
            "yellow": "#F5AE2E"
        },
        {
            "background": "#1B1B1B",
            "black": "#1B1B1B",
            "blue": "#458588",
            "brightBlack": "#928374",
            "brightBlue": "#83A598",
            "brightCyan": "#8EC07C",
            "brightGreen": "#B8BB26",
            "brightPurple": "#D3869B",
            "brightRed": "#FB4934",
            "brightWhite": "#EBDBB2",
            "brightYellow": "#FABD2F",
            "cursorColor": "#EBDBB2",
            "cyan": "#689D6A",
            "foreground": "#EBDBB2",
            "green": "#98971A",
            "name": "GruvboxDarkHard",
            "purple": "#B16286",
            "red": "#CC241D",
            "selectionBackground": "#665C54",
            "white": "#A89984",
            "yellow": "#D79921"
        },
        {
            "background": "#2C2525",
            "black": "#403838",
            "blue": "#F38D70",
            "brightBlack": "#72696A",
            "brightBlue": "#F38D70",
            "brightCyan": "#85DACC",
            "brightGreen": "#ADDA78",
            "brightPurple": "#A8A9EB",
            "brightRed": "#FD6883",
            "brightWhite": "#FFF1F3",
            "brightYellow": "#F9CC6C",
            "cursorColor": "#FFF1F3",
            "cyan": "#85DACC",
            "foreground": "#FFF1F3",
            "green": "#ADDA78",
            "name": "Monokai Pro (Filter Ristretto)",
            "purple": "#A8A9EB",
            "red": "#FD6883",
            "selectionBackground": "#C3B7B8",
            "white": "#FFF1F3",
            "yellow": "#F9CC6C"
        },
        {
            "background": "#0C0C0C",
            "black": "#1A1A1A",
            "blue": "#9D65FF",
            "brightBlack": "#625E4C",
            "brightBlue": "#9D65FF",
            "brightCyan": "#58D1EB",
            "brightGreen": "#98E024",
            "brightPurple": "#F4005F",
            "brightRed": "#F4005F",
            "brightWhite": "#F6F6EF",
            "brightYellow": "#E0D561",
            "cursorColor": "#FC971F",
            "cyan": "#58D1EB",
            "foreground": "#D9D9D9",
            "green": "#98E024",
            "name": "Monokai Remastered",
            "purple": "#F4005F",
            "red": "#F4005F",
            "selectionBackground": "#343434",
            "white": "#C4C5B5",
            "yellow": "#FD971F"
        },
        {
            "background": "#1A1A1A",
            "black": "#1A1A1A",
            "blue": "#9D65FF",
            "brightBlack": "#625E4C",
            "brightBlue": "#9D65FF",
            "brightCyan": "#58D1EB",
            "brightGreen": "#98E024",
            "brightPurple": "#F4005F",
            "brightRed": "#F4005F",
            "brightWhite": "#F6F6EF",
            "brightYellow": "#E0D561",
            "cursorColor": "#F6F7EC",
            "cyan": "#58D1EB",
            "foreground": "#C4C5B5",
            "green": "#98E024",
            "name": "Monokai Soda",
            "purple": "#F4005F",
            "red": "#F4005F",
            "selectionBackground": "#343434",
            "white": "#C4C5B5",
            "yellow": "#FA8419"
        },
        {
            "background": "#121212",
            "black": "#121212",
            "blue": "#0443FF",
            "brightBlack": "#838383",
            "brightBlue": "#0443FF",
            "brightCyan": "#51CEFF",
            "brightGreen": "#B1E05F",
            "brightPurple": "#F200F6",
            "brightRed": "#F6669D",
            "brightWhite": "#FFFFFF",
            "brightYellow": "#FFF26D",
            "cursorColor": "#FB0007",
            "cyan": "#01B6ED",
            "foreground": "#F9F9F9",
            "green": "#98E123",
            "name": "Monokai Vivid",
            "purple": "#F800F8",
            "red": "#FA2934",
            "selectionBackground": "#FFFFFF",
            "white": "#FFFFFF",
            "yellow": "#FFF30A"
        },
        {
            "background": "#191724",
            "black": "#706E86",
            "blue": "#31748F",
            "brightBlack": "#706E86",
            "brightBlue": "#31748F",
            "brightCyan": "#EBBCBA",
            "brightGreen": "#9CCFD8",
            "brightPurple": "#C4A7E7",
            "brightRed": "#EB6F92",
            "brightWhite": "#E0DEF4",
            "brightYellow": "#F6C177",
            "cursorColor": "#FFFFFF",
            "cyan": "#EBBCBA",
            "foreground": "#E0DEF4",
            "green": "#9CCFD8",
            "name": "Rose Pine",
            "purple": "#C4A7E7",
            "red": "#EB6F92",
            "selectionBackground": "#FFFFFF",
            "white": "#E0DEF4",
            "yellow": "#F6C177"
        },
        {
            "background": "#300A24",
            "black": "#2E3436",
            "blue": "#3465A4",
            "brightBlack": "#555753",
            "brightBlue": "#729FCF",
            "brightCyan": "#34E2E2",
            "brightGreen": "#8AE234",
            "brightPurple": "#AD7FA8",
            "brightRed": "#EF2929",
            "brightWhite": "#EEEEEC",
            "brightYellow": "#FCE94F",
            "cursorColor": "#BBBBBB",
            "cyan": "#06989A",
            "foreground": "#EEEEEC",
            "green": "#4E9A06",
            "name": "Ubuntu",
            "purple": "#75507B",
            "red": "#CC0000",
            "selectionBackground": "#B5D5FF",
            "white": "#D3D7CF",
            "yellow": "#C4A000"
        },
        {
            "background": "#000000",
            "black": "#000000",
            "blue": "#82AAFF",
            "brightBlack": "#333333",
            "brightBlue": "#B4CCFF",
            "brightCyan": "#B8EAFF",
            "brightGreen": "#DBF1BA",
            "brightPurple": "#DDBDF2",
            "brightRed": "#F6A9AE",
            "brightWhite": "#FFFFFF",
            "brightYellow": "#FFDFA6",
            "cursorColor": "#FEFEFE",
            "cyan": "#89DDFF",
            "foreground": "#FFFFFF",
            "green": "#C3E88D",
            "name": "UltraDark",
            "purple": "#C792EA",
            "red": "#F07178",
            "selectionBackground": "#222222",
            "white": "#CCCCCC",
            "yellow": "#FFCB6B"
        },
        {
            "background": "#242728",
            "black": "#242728",
            "blue": "#47E0FB",
            "brightBlack": "#636667",
            "brightBlue": "#7FECFF",
            "brightCyan": "#69FCD3",
            "brightGreen": "#DEFF8C",
            "brightPurple": "#E681FF",
            "brightRed": "#FB58B4",
            "brightWhite": "#F9F9F5",
            "brightYellow": "#EBE087",
            "cursorColor": "#C1C1C1",
            "cyan": "#0EFFBB",
            "foreground": "#C1C1C1",
            "green": "#B6FF00",
            "name": "UltraViolent",
            "purple": "#D731FF",
            "red": "#FF0090",
            "selectionBackground": "#574C49",
            "white": "#E1E1E1",
            "yellow": "#FFF727"
        },
        {
            "background": "#101010",
            "black": "#101010",
            "blue": "#ACA1CF",
            "brightBlack": "#7E7E7E",
            "brightBlue": "#B9AEDA",
            "brightCyan": "#F591B2",
            "brightGreen": "#99FFE4",
            "brightPurple": "#ECAAD6",
            "brightRed": "#FF8080",
            "brightWhite": "#FFFFFF",
            "brightYellow": "#FFC799",
            "cursorColor": "#ACB1AB",
            "cyan": "#EA83A5",
            "foreground": "#FFFFFF",
            "green": "#90B99F",
            "name": "Vesper",
            "purple": "#E29ECA",
            "red": "#F5A191",
            "selectionBackground": "#988049",
            "white": "#A0A0A0",
            "yellow": "#E6B99D"
        },
        {
            "background": "#000000",
            "black": "#878787",
            "blue": "#44B4CC",
            "brightBlack": "#555555",
            "brightBlue": "#0000FF",
            "brightCyan": "#00FFFF",
            "brightGreen": "#00FF00",
            "brightPurple": "#FF00FF",
            "brightRed": "#FF0000",
            "brightWhite": "#E5E5E5",
            "brightYellow": "#FFFF00",
            "cursorColor": "#FFFFFF",
            "cyan": "#44B4CC",
            "foreground": "#FFFFFF",
            "green": "#CCFF04",
            "name": "VibrantInk",
            "purple": "#9933CC",
            "red": "#FF6600",
            "selectionBackground": "#B5D5FF",
            "white": "#F5F5F5",
            "yellow": "#FFCC00"
        },
        {
            "background": "#0F1419",
            "black": "#000000",
            "blue": "#36A3D9",
            "brightBlack": "#323232",
            "brightBlue": "#68D5FF",
            "brightCyan": "#C7FFFD",
            "brightGreen": "#EAFE84",
            "brightPurple": "#FFA3AA",
            "brightRed": "#FF6565",
            "brightWhite": "#FFFFFF",
            "brightYellow": "#FFF779",
            "cursorColor": "#F29718",
            "cyan": "#95E6CB",
            "foreground": "#E6E1CF",
            "green": "#B8CC52",
            "name": "ayu",
            "purple": "#F07178",
            "red": "#FF3333",
            "selectionBackground": "#253340",
            "white": "#FFFFFF",
            "yellow": "#E7C547"
        },
        {
            "name": "Broadcast",
            "black": "#000000",
            "red": "#da4939",
            "green": "#519f50",
            "yellow": "#ffd24a",
            "blue": "#6d9cbe",
            "purple": "#d0d0ff",
            "cyan": "#6e9cbe",
            "white": "#ffffff",
            "brightBlack": "#323232",
            "brightRed": "#ff7b6b",
            "brightGreen": "#83d182",
            "brightYellow": "#ffff7c",
            "brightBlue": "#9fcef0",
            "brightPurple": "#ffffff",
            "brightCyan": "#a0cef0",
            "brightWhite": "#ffffff",
            "background": "#2b2b2b",
            "foreground": "#e6e1dc",
            "selectionBackground": "#5a647e",
            "cursorColor": "#ffffff"
        },
        {
            "name": "Calamity",
            "black": "#2f2833",
            "red": "#fc644d",
            "green": "#a5f69c",
            "yellow": "#e9d7a5",
            "blue": "#3b79c7",
            "purple": "#f92672",
            "cyan": "#74d3de",
            "white": "#d5ced9",
            "brightBlack": "#7e6c88",
            "brightRed": "#fc644d",
            "brightGreen": "#a5f69c",
            "brightYellow": "#e9d7a5",
            "brightBlue": "#3b79c7",
            "brightPurple": "#f92672",
            "brightCyan": "#74d3de",
            "brightWhite": "#ffffff",
            "background": "#2f2833",
            "foreground": "#d5ced9",
            "selectionBackground": "#7e6c88",
            "cursorColor": "#d5ced9"
        },
        {
            "name": "Catppuccin Mocha",
            "black": "#45475a",
            "red": "#f38ba8",
            "green": "#a6e3a1",
            "yellow": "#f9e2af",
            "blue": "#89b4fa",
            "purple": "#f5c2e7",
            "cyan": "#94e2d5",
            "white": "#bac2de",
            "brightBlack": "#585b70",
            "brightRed": "#f38ba8",
            "brightGreen": "#a6e3a1",
            "brightYellow": "#f9e2af",
            "brightBlue": "#89b4fa",
            "brightPurple": "#f5c2e7",
            "brightCyan": "#94e2d5",
            "brightWhite": "#a6adc8",
            "background": "#1e1e2e",
            "foreground": "#cdd6f4",
            "selectionBackground": "#585b70",
            "cursorColor": "#f5e0dc"
        },
        {
            "name": "Chalkboard",
            "black": "#000000",
            "red": "#c37372",
            "green": "#72c373",
            "yellow": "#c2c372",
            "blue": "#7372c3",
            "purple": "#c372c2",
            "cyan": "#72c2c3",
            "white": "#d9d9d9",
            "brightBlack": "#323232",
            "brightRed": "#dbaaaa",
            "brightGreen": "#aadbaa",
            "brightYellow": "#dadbaa",
            "brightBlue": "#aaaadb",
            "brightPurple": "#dbaada",
            "brightCyan": "#aadadb",
            "brightWhite": "#ffffff",
            "background": "#29262f",
            "foreground": "#d9e6f2",
            "selectionBackground": "#073642",
            "cursorColor": "#d9e6f2"
        },
        {
            "name": "Espresso",
            "black": "#353535",
            "red": "#d25252",
            "green": "#a5c261",
            "yellow": "#ffc66d",
            "blue": "#6c99bb",
            "purple": "#d197d9",
            "cyan": "#bed6ff",
            "white": "#eeeeec",
            "brightBlack": "#535353",
            "brightRed": "#f00c0c",
            "brightGreen": "#c2e075",
            "brightYellow": "#e1e48b",
            "brightBlue": "#8ab7d9",
            "brightPurple": "#efb5f7",
            "brightCyan": "#dcf4ff",
            "brightWhite": "#ffffff",
            "background": "#323232",
            "foreground": "#ffffff",
            "selectionBackground": "#5b5b5b",
            "cursorColor": "#d6d6d6"
        },
        {
            "name": "Flatland",
            "black": "#1d1d19",
            "red": "#f18339",
            "green": "#9fd364",
            "yellow": "#f4ef6d",
            "blue": "#5096be",
            "purple": "#695abc",
            "cyan": "#d63865",
            "white": "#ffffff",
            "brightBlack": "#1d1d19",
            "brightRed": "#d22a24",
            "brightGreen": "#a7d42c",
            "brightYellow": "#ff8949",
            "brightBlue": "#61b9d0",
            "brightPurple": "#695abc",
            "brightCyan": "#d63865",
            "brightWhite": "#ffffff",
            "background": "#1d1f21",
            "foreground": "#b8dbef",
            "selectionBackground": "#2b2a24",
            "cursorColor": "#708284"
        },
        {
            "name": "flexoki-dark",
            "black": "#1c1b1a",
            "red": "#d14d41",
            "green": "#879a39",
            "yellow": "#d0a215",
            "blue": "#4385be",
            "purple": "#ce5d97",
            "cyan": "#3aa99f",
            "white": "#b7b5ac",
            "brightBlack": "#575653",
            "brightRed": "#d14d41",
            "brightGreen": "#879a39",
            "brightYellow": "#d0a215",
            "brightBlue": "#4385be",
            "brightPurple": "#ce5d97",
            "brightCyan": "#3aa99f",
            "brightWhite": "#cecdc3",
            "background": "#1c1b1a",
            "foreground": "#cecdc3",
            "selectionBackground": "#cecdc3",
            "cursorColor": "#cecdc3"
        },
        {
            "name": "ForestBlue",
            "black": "#333333",
            "red": "#f8818e",
            "green": "#92d3a2",
            "yellow": "#1a8e63",
            "blue": "#8ed0ce",
            "purple": "#5e468c",
            "cyan": "#31658c",
            "white": "#e2d8cd",
            "brightBlack": "#3d3d3d",
            "brightRed": "#fb3d66",
            "brightGreen": "#6bb48d",
            "brightYellow": "#30c85a",
            "brightBlue": "#39a7a2",
            "brightPurple": "#7e62b3",
            "brightCyan": "#6096bf",
            "brightWhite": "#e2d8cd",
            "background": "#051519",
            "foreground": "#e2d8cd",
            "selectionBackground": "#4d4d4d",
            "cursorColor": "#9e9ecb"
        }
    ],
    "themes":
    [],
    "useAcrylicInTabRow": true
}